iphub/__init__.py
iphub/iphub.py
iphub-1.0.2.dist-info/LICENSE
iphub-1.0.2.dist-info/METADATA
iphub-1.0.2.dist-info/WHEEL
iphub-1.0.2.dist-info/top_level.txt
iphub-1.0.2.dist-info/RECORD
