Metadata-Version: 2.1
Name: iphub
Version: 1.0.2
Summary: IPhub.info API wrapper.
Home-page: https://github.com/DedInc/iphub
Author: Maehdakvan
Author-email: visitanimation@google.com
Project-URL: Bug Tracker, https://github.com/DedInc/iphub/issues
Classifier: Programming Language :: Python :: 3
Classifier: License :: OSI Approved :: MIT License
Classifier: Operating System :: OS Independent
Requires-Python: >=3.6
License-File: LICENSE
Requires-Dist: requests
